{
  "$schema": "http://schema.management.azure.com/schemas/2015-01-01/deploymentParameters.json#",
  "contentVersion": "1.0.0.0",
  "parameters": {
    "vmSku": {
      "value": "Standard_D4"
    },
    "vmssName": {
      "value": "your-vmss"
    },
    "instanceCount": {
      "value": 2
    },
    "adminUsername": {
      "value": "user"
    },
    "adminPassword": {
      "value": "password"
    },
    "aadClientID": {
      "value": "aadClientId"
    },
    "aadClientSecret": {
      "value": "aadClientSecret"
    },
    "keyVaultName": {
      "value": "yourVault"
    },
    "keyVaultResourceGroup": {
      "value": "KeyVaultResGroup"
    },
    "useExistingKek": {
      "value": "nokek"
    },
    "keyEncryptionKeyURL": {
      "value": "KekUrl"
    },
    "volumeType": {
      "value": "All"
    },
    "sequenceVersion": {
      "value": "1.0"
    }
	
  }
}
